{
  "accountAssociation": {
    "header": "eyJmaWQiOjY3MzEyNiwidHlwZSI6ImF1dGgiLCJrZXkiOiIweDQ2RkU3ZDUxRTNiOTA4MENDY0VDMTJBNjc1ZjYzQzg5MkEyYzBEM0YifQ",
    "payload": "eyJkb21haW4iOiJodHRwczovL2ZhcmNhc3RlcnNuYWtlLnZlcmNlbC5hcHAvIn0",
    "signature": "pyrzknkj7Y8xOG9YAUxZk4byaKhvuIs5px5kXdgAx3lCC6f1JFrQQknckAzB/PycRLmcz77OhpoMqYEkE5Fs7Bw="
  },
  "frame": {
    "name": "Farcaster Snake",
    "version": "1",
    "iconUrl": "https://farcastersnake.vercel.app/logo.jpg",
    "homeUrl": "https://farcastersnake.vercel.app",
    "imageUrl": "https://farcastersnake.vercel.app/logo.jpg",
    "buttonTitle": "Open Farcaster Snake",
    "splashImageUrl": "https://farcastersnake.vercel.app/splash.png",
    "splashBackgroundColor": "#8b5cf6",
    "subtitle": "Eat Drink Poop Repeat",
    "description": "Farcaster Snake is a social game. Eat to grow, drink to survive, poop or die. Compete on leaderboards, challenge friends, and score over 50 to earn rewards",
    "primaryCategory": "games",
    "screenshotUrls": ["https://farcastersnake.vercel.app/screenshot.png"],
    "tagline": "Eat, Drink, Poop. Repeat "
  }
}
